{
  "login_number": "Uimhir teileafón",
  "login_button": "Ar Aghaidh",
  "otp_button": "Logáil isteach",
  "title": "Cúnant",
  "enter_otp": "Iontráil OTP",
  "self_register": "Féinchlárú",
  "username": "Ainm iomlán",
  "user_dob": "Dáta Breithe (DD / MM / BBBB)",
  "male": "Fireann",
  "female": "Mná",
  "other": "An Tríú Inscne",
  "IdName": "Roghnaigh Cineál Doiciméid Aitheantais",
  "idNo": "Uimhir doiciméad aitheantais",
  "user_address": "Seoladh",
  "cancel_button": "Cealaigh",
  "register_button": "Cláraigh",
  "cancel_msg": "An bhfuil tú cinnte ag iarraidh cealú?",
  "yes_button": "Sea",
  "no_button": "Níl",
  "home_title": "Baile",
  "history_title": "Stair",
  "RaiseHand_title": "Teastaionn Cabhair",
  "update_health_title": "Sláinte a Nuashonrú",
  "profile_title": "Próifíl",
  "profile_name": "Ainm an othair",
  "health_officer": "Do oifigeach sláinte",
  "contact": "TEAGMHÁIL",
  "now-update": "Thabhairt cothrom le dáta ANOIS",
  "last_health": "Do nuashonrú sláinte deireanach",
  "today": "Inniu",
  "em_contact": "D’uimhir teagmhála éigeandála",
  "location": "Do shuíomh reatha",
  "location_button": "Suíomh Nuashonraithe",
  "health-info": "Nuashonraíodh d’fhaisnéis sláinte",
  "cough": "An bhfuil casacht ort?",
  "fever": "An bhfuil fiabhras ort?",
  "chills": "An bhfuil chills agat?",
  "breath": "An bhfuil deacracht análaithe agat?",
  "timestamp": "Timestamp",
  "qus1": "Conas tá tú?",
  "qus2": "I gcomparáid le inné nó níos luaithe inniu, tá do shláinte ...",
  "qus3": "Eolas roghnach:",
  "better": "Ag éirí níos fearr",
  "worse": "Ag dul in olcas",
  "re-same": "Fanacht mar an gcéanna",
  "temp": "Teocht (° C)",
  "heart-rate": "Ráta Croí / Pulse (in aghaidh an nóiméid)",
  "respiratory": "Ráta riospráide (in aghaidh an nóiméid)",
  "spo2": "SpO2 (%)",
  "update_button": "Nuashonrú",
  "quarantine-officer": "Déan teagmháil le d’oifigeach coraintín",
  "medical-officer": "Déan teagmháil le d’oifigeach sláinte",
  "food": "Iarr bia / uisce / cógais éigeandála",
  "your hand": "Iarr cabhair",
  "comments": "Nótaí tráchta",
  "submit": "Cuir isteach"
}
